Workbook

Sheet Instructions
A1: EMD (Essential Model Documentation) Template - v0.993
A4: Overview
A5: This template allows you to document an Earth System Model according to the EMD specification.
A6: The EMD captures essential information about model configuration for CMIP7 and other projects.
A8: How to Use This Template
A9: 1. Go to 'COMPONENT_SELECTOR' sheet and select which components are Dynamic/Prescribed/Omitted
A10: 2. Return to 'Top-Level Model' sheet - component fields will auto-populate!
A11: 3. Fill other top-level properties and check the validation panel
A12: 4. Add references in 'References' sheet (you'll need Reference IDs later)
A13: 5. Create grid definitions in 'Horizontal Grid' and 'Vertical Grid' sheets
A14: 6. Document each dynamic component in 'Model Components' sheet
A15: 7. All dropdowns pull values from CV_* (Controlled Vocabulary) sheets
... A46: Contact: CMIP7 Documentation Task Team

Sheet Top-Level Model
A1: Property | B1: Value | C1: Description | D1: Example | E1: Required
A2: name | B2: CNRM-ESM2-1e | C2: The name of the top-level model (will be source_id in CMIP7) | D2: HadGEM3-GC31-HH | E2: Yes
A3: family | B3: CNRM-CM, CNRM-ESM | C3: Model family name (use 'none' if no family) | D3: HadGEM3 | E3: Yes
A4: dynamic_components | B4: =COMPONENT_SELECTOR!E13 -> aerosol,atmosphere,atmospheric_chemistry,land_surface,ocean,ocean_biogeochemistry,sea_ice | C4: Components dynamically simulated → Use COMPONENT SELECTOR below ↓ | D4: atmosphere,ocean,sea_ice | E4: Yes
A5: prescribed_components | B5: =COMPONENT_SELECTOR!E14 | C5: Components with prescribed values → Use COMPONENT SELECTOR below ↓ | D5: atmospheric_chemistry | E5: No
A6: omitted_components | B6: =COMPONENT_SELECTOR!E15 -> land_ice | C6: Components wholly omitted → Use COMPONENT SELECTOR below ↓ | D6: aerosol | E6: No
A7: description | B7: CNRM-ESM2-1e is the CNRM Earth System model version 2 designed for CMIP6 on the basis of the physical core CNRM-CM6-1 (Voldoire et al. 2019). In concentration mode, it is the same model as CNRM-ESM2-1 (Séférian et al. 2019), it only differs from CNRM-ESM2-1 in emission-driven mode (see Bossert et al. 2026). The main adaptations consist in a better consevration of the carbon in all the components leading to a more consistent/realistic carbon flux evolution in historical simulations. The atmospheric is represented based on ARPEGE-Climat V6.3 online coupled to the land, terrestrial biophere and lakes components included in the SURFEX v8.0 platform. The pronostic aerosols scheme TACTIC v2 is embedded in the atmospheric component as well as the stratospheric chemistry scheme REPROBUS v2. The water budget is closed by the river routing scheme CTRIP v2. NEMO3.6 is implemented to represent the ocean along with GELATO v6 for the seaice. The ocean biogeochemistry is simulated using the PISCES v2-gas model. Land ice-sheet are not represented, the snow mass budget over these icesheet and land glaciers is directly fed to the ocean. | C7: Brief free-text scientific overview of the model | D7: The model includes... | E7: Yes
A8: calendar | B8: standard | C8: Calendar(s) used (comma-separated, from CV_Calendar) | D8: standard | E8: Yes
A9: release_year | B9: 2018 | C9: Year model was released or first used for publications | D9: 2016 | E9: Yes
A10: 💡 TIP: | B10: To select components, go to the 'COMPONENT_SELECTOR' sheet → Choose Yes/No for each component → Values will auto-fill above
A12: 📊 MODEL DOCUMENTATION STATUS
A13: Automatic validation of model documentation completeness and consistency
A15: Check | B15: Status | C15: Details | D15: Sheet | E15: Action Required
A16: 1. Required Top-Level Fields | B16: =IF(AND(B2<>"", B3<>"", B4<>"", B6<>"", B7<>"", B8<>""), "✓ OK", IF(OR(B2="", B3="", B4="", B6="", B7="", B8=""), "✗ Missing", "⚠ Check")) -> ✓ OK | C16: name, family, dynamic_components, description, calendar, release_year | D16: Top-Level Model | E16: Fill all required fields (rows 2-9)
A17: 2. Dynamic Components Documented | B17: =IF(B4="", "⚠ N/A", IF(COUNTIF('Model Components'!B4:B100, "?*")>=1, "✓ OK", "✗ Missing")) -> ✓ OK | C17: Each component in dynamic_components must have a row in Model Components | D17: Model Components | E17: Add component rows for each dynamic component
A18: 3. Component Grids Defined | B18: =IF(COUNTIF('Model Components'!B4:B100, "?*")=0, "⚠ N/A", IF(AND(COUNTIF('Model Components'!I4:I100, "?*")>=1, COUNTIF('Model Components'!J4:J100, "?*")>=1), "✓ OK", "✗ Missing")) -> ✓ OK | C18: All components must have horizontal_grid_id and vertical_grid_id | D18: Model Components | E18: Specify grid IDs for all components
A19: 4. Horizontal Grids Exist | B19: =IF(COUNTIF('Horizontal Grid'!A:A, "HGRID*")>=1, "✓ OK", "✗ Missing") -> ✓ OK | C19: At least one horizontal grid must be defined | D19: Horizontal Grid | E19: Define horizontal grids matching component grid IDs
A20: 5. Vertical Grids Exist | B20: =IF(COUNTIF('Vertical Grid'!A:A, "VGRID*")>=1, "✓ OK", "✗ Missing") -> ✓ OK | C20: At least one vertical grid must be defined | D20: Vertical Grid | E20: Define vertical grids matching component grid IDs
A21: 6. References Provided | B21: =IF(COUNTIF(References!A:A, "REF*")>=1, "✓ OK", "✗ Missing") -> ✓ OK | C21: At least one reference must be provided for model and components | D21: References | E21: Add references with DOIs
A22: 7. Component References Linked | B22: =IF(COUNTIF('Model Components'!K4:K100, "?*")>=1, "✓ OK", "⚠ Check") -> ✓ OK | C22: Components should reference publications | D22: Model Components | E22: Add reference_ids to component rows
A23: 8. Grid Resolution Data | B23: =IF(AND(COUNTIF('Horizontal Grid'!S:S, ">0")>=1, COUNTIF('Horizontal Grid'!U:U, ">0")>=1), "✓ OK", "⚠ Check") -> ✓ OK | C23: Grids should have resolution_range and mean_resolution | D23: Horizontal Grid | E23: Calculate grid resolutions
A24: 9. Embedded/Coupled Exclusivity | B24: =IF(COUNTIF('Model Components'!B4:B100, "?*")=0, "⚠ N/A", "⚠ Manual") -> ⚠ Manual | C24: Components must be either embedded OR coupled, not both | D24: Model Components | E24: Verify embedded_in and coupled_with are mutually exclusive
A25: 10. Grid Units Consistency | B25: =IF(COUNTIF('Horizontal Grid'!M:M, "?*")>=1, "✓ OK", "⚠ Check") -> ✓ OK | C25: Horizontal grids with resolutions must have units specified | D25: Horizontal Grid | E25: Specify horizontal_units when resolution_x/y are filled
A27: =CONCATENATE("Overall Status: ", COUNTIF(B16:B25, "✓*"), " OK | ", COUNTIF(B16:B25, "✗*"), " Missing | ", COUNTIF(B16:B25, "⚠*"), " Warnings") -> Overall Status: 9 OK | 0 Missing | 1 Warnings
A29: Legend:
A30: ✓ OK | B30: Check passed - requirement met
A31: ✗ Missing | B31: Required data is missing - action needed
A32: ⚠ Warning | B32: Review needed or not applicable

Sheet COMPONENT_SELECTOR
A1: Component | B1: Dynamic? | C1: Prescribed? | D1: Omitted?
A2: aerosol | B2: Yes | C2: No | D2: No
A3: atmosphere | B3: Yes | C3: No | D3: No
A4: atmospheric_chemistry | B4: Yes | C4: No | D4: No
A5: land_surface | B5: Yes | C5: No | D5: No
A6: land_ice | B6: No | C6: No | D6: Yes
A7: ocean | B7: Yes | C7: No | D7: No
A8: ocean_biogeochemistry | B8: Yes | C8: No | D8: No
A9: sea_ice | B9: Yes | C9: No | D9: No
A12: #NAME? | B12: Raw | C12: Step 1 | D12: Step 2 | E12: FINAL
A13: Dynamic Components Result: | B13: =TRIM(CONCATENATE(IF(B2="Yes",CONCATENATE(A2,","),""),IF(B3="Yes",CONCATENATE(A3,","),""),IF(B4="Yes",CONCATENATE(A4,","),""),IF(B5="Yes",CONCATENATE(A5,","),""),IF(B6="Yes",CONCATENATE(A6,","),""),IF(B7="Yes",CONCATENATE(A7,","),""),IF(B8="Yes",CONCATENATE(A8,","),""),IF(B9="Yes",CONCATENATE(A9,","),""))) -> aerosol,atmosphere,atmospheric_chemistry,land_surface,ocean,ocean_biogeochemistry,sea_ice, | C13: =SUBSTITUTE(B13,",,",",") -> aerosol,atmosphere,atmospheric_chemistry,land_surface,ocean,ocean_biogeochemistry,sea_ice, | D13: =IF(LEFT(C13,1)=",",MID(C13,2,LEN(C13)),C13) -> aerosol,atmosphere,atmospheric_chemistry,land_surface,ocean,ocean_biogeochemistry,sea_ice, | E13: =IF(RIGHT(D13,1)=",",LEFT(D13,LEN(D13)-1),D13) -> aerosol,atmosphere,atmospheric_chemistry,land_surface,ocean,ocean_biogeochemistry,sea_ice
A14: Prescribed Components Result: | B14: =TRIM(CONCATENATE(IF(C2="Yes",CONCATENATE(A2,","),""),IF(C3="Yes",CONCATENATE(A3,","),""),IF(C4="Yes",CONCATENATE(A4,","),""),IF(C5="Yes",CONCATENATE(A5,","),""),IF(C6="Yes",CONCATENATE(A6,","),""),IF(C7="Yes",CONCATENATE(A7,","),""),IF(C8="Yes",CONCATENATE(A8,","),""),IF(C9="Yes",CONCATENATE(A9,","),""))) | C14: =SUBSTITUTE(B14,",,",",") | D14: =IF(LEFT(C14,1)=",",MID(C14,2,LEN(C14)),C14) | E14: =IF(RIGHT(D14,1)=",",LEFT(D14,LEN(D14)-1),D14)
A15: Omitted Components Result: | B15: =TRIM(CONCATENATE(IF(D2="Yes",CONCATENATE(A2,","),""),IF(D3="Yes",CONCATENATE(A3,","),""),IF(D4="Yes",CONCATENATE(A4,","),""),IF(D5="Yes",CONCATENATE(A5,","),""),IF(D6="Yes",CONCATENATE(A6,","),""),IF(D7="Yes",CONCATENATE(A7,","),""),IF(D8="Yes",CONCATENATE(A8,","),""),IF(D9="Yes",CONCATENATE(A9,","),""))) -> land_ice, | C15: =SUBSTITUTE(B15,",,",",") -> land_ice, | D15: =IF(LEFT(C15,1)=",",MID(C15,2,LEN(C15)),C15) -> land_ice, | E15: =IF(RIGHT(D15,1)=",",LEFT(D15,LEN(D15)-1),D15) -> land_ice
A17: 📝 How to use:
A18: 1. Select 'Yes' in Dynamic/Prescribed/Omitted columns for each component
A19: 2. The FINAL column (E) shows the result with correct formatting
A20: 3. These values automatically appear in Top-Level Model sheet
A21: 4. The validation panel will update when you return to Top-Level Model

Sheet Model Components
A1: Component ID | B1: component | C1: name | D1: family | E1: description | F1: code_base | G1: embedded_in | H1: coupled_with | I1: horizontal_grid_id | J1: vertical_grid_id | K1: reference_ids
A2: Unique ID for this component (e.g., COMP001) | B2: Component type (DROPDOWN from CV_Component) | C2: Component name | D2: Family name (or 'none') | E2: Scientific overview | F2: URL/DOI for source code (or 'private') | G2: Host component if embedded (DROPDOWN from CV_Component) | H2: Coupled components (comma-separated, from CV_Component) | I2: ID of horizontal grid (reference to Horizontal Grid sheet) | J2: ID of vertical grid (reference to Vertical Grid sheet) | K2: Reference IDs (comma-separated, from References sheet)
A3: COMP001 | B3: atmosphere | C3: HadAM3 | D3: HadAM | E3: Dynamical, thermodynamical, and physical processes in the atmosphere... | F3: https://doi.org/10.5281/zenodo.xxx | H3: ocean,sea_ice,land_surface | I3: HGRID001 | J3: VGRID001 | K3: REF001,REF002
A4: COMP001 | B4: aerosol | C4: TACTIC | D4: none | E4: TACTIC (Tropospheric Aerosols for ClimaTe In CNRM) is an interactive tropospheric aerosol scheme, able to represent the main anthropogenic and natural aerosol types in the troposphere. Originally developed in the GEMS/MACC project (Morcrette et al., 2009), this scheme has been adapted to the ARPEGE/ALADIN-Climat models (Michou et al., 2015 and Nabat et al., 2015). Aerosols are included through sectional bins, separating desert dust (3 size bins), sea-salt (3 size bins), sulphate (1 bin, as well as 1 additional variable for sulfate precursors considered as SO2), organic matter (2 bins: hydrophobic and hydrophilic particles) and black carbon (2 bins: hydrophobic and hydrophilic particles) particles. All these 12 species are prognostic variables in the model, submitted to transport (semi-lagrangian advection, and convective transport), dry deposition, in-cloud and below-cloud scavenging. The interaction with shortwave and longwave radiation, is also taken into account through optical properties (extinction coefficient, single scattering albedo and asymmetry parameter) calculated using the Mie theory. Sulfate, organic matter and sea salt concentrations are used to determine the cloud droplet number concentration following Menon et al. (2002), thus representing the cloud-albedo effect (1st indirect aerosol effect). | F4: private | G4: atmosphere | I4: HGRID001 | J4: VGRID001 | K4: REF004
B5: atmosphere | C5: Arpege-Climat Version 6.3 | D5: Arpege-Climat | E5: ARPEGE-Climat Version 6.3 is the atmospheric component of the CNRM climate and Earth System models (CNRM-CM6-1 and CNRM-ESM2-1). It is based on the cycle 37 of the ARPEGE/IFS model (declared in 2010), developed under a collaboration between Météo-France and ECMWF. ARPEGE-Climat shares a large part of its physics and dynamics with its NWP counterpart ARPEGE used operationnally at Météo-France. In comparison to ARPEGE-Climat Version 5.1 used for the CMIP5 exercice in CNRM-CM5.1, most of the atmospheric physics has been updated or revisited (Roehrig et al. 2019, Voldoire et al. 2019). For the surface, it is coupled to the SURFEX platform (Decharme et al. 2019). | F5: private | H5: land_surface,ocean | I5: HGRID001 | J5: VGRID001 | K5: REF005
B6: atmospheric_chemistry | C6: REPROBUS-C (v2.0) | D6: REPROBUS | E6: The chemistry scheme of CNRM-ESM2 was first implemented and evaluated in Michou et al. (2011), and more recently during the course of the Chemistry Climate Model Initiative (CCMI) research (e.g., Morgenstern et al. (2017); Wales et al. (2018); Maycock et al. (2018a,b); Zhang et al. (2018)). It is an “on-line” scheme whereby the chemistry routines are part of the physics of the atmospheric climate model and called at each time-step of the physics. The scheme does not represent the low troposphere ozone non-methane hydrocarbon chemistry and considers 63 chemistry species that are prognostic variables of the climate model. Chemical evolution is computed down to the 560 hPa level (for details see Michou et al. (2011) and Morgenstern et al. (2017)). Below this level, the concentration of a number of species are relaxed towards the yearly evolving global mean abundances of CMIP6 (Meinshausen et al. (2017)); for the other species concentrations below 560 hPa level are relaxed towards the 560 hPa value. Coherently with the relaxation, explicit emissions, dry deposition, wash-out and parameterised transport (diffusion and convection) of the chemical fields are not considered. The 3-D concentrations of H2O, CO2 , O3 , CH4 , N2O, CFC11, and CFC12 are transferred to the radiative code. | F6: private | G6: atmosphere | I6: HGRID001 | J6: VGRID001 | K6: REF004
B7: land_surface | C7: SURFEX v8 modeling platform | D7: SURFEX | E7: SURFEXv8.0 encompasses several submodules for modeling the interactions between the atmosphere, the ocean, the lakes and the land surface. The land surface is represented using the new ISBA-CTRIP coupled system (Decharme et al., 2019; Delire et al. 2019). ISBA calculates the time evolution of the energy, carbon and water budgets at the land surface while CTRIP simulates river discharges (including carbon transport) up to the ocean from the total runoff (and total soil carbon leaching) computed by ISBA. The FLAKE model simulate surface fluxes over lakes, including both the Caspian and the Aral seas, and computes the temporal evolution of the vertical lake temperature profile from the surface mixing layer to the bottom (Le Moigne et al. 2016). | F7: https://www.umr-cnrm.fr/surfex/spip.php?rubrique8 | H7: atmosphere,ocean | I7: HGRID001 | J7: VGRID002 | K7: REF006,REF007,REF008,REF009
B8: ocean | C8: NEMO : Nucleus for European Modelling of the Ocean version 3.6 (OPA) | D8: NEMO | E8: The ocean component of CNRM-ESM2-1 (Séférian et al. 2019) is based on the version 3.6 of NEMO (Nucleus for European Models of the Ocean ; Madec, 2016). At the surface, the model uses the split-explicit non-linear free surface formulation proposed by Shchepetkin and McWilliams (2005), with a variable volume. Seawater thermodynamics uses the equation of state defined in the Thermodynamic Equation of State 2010 (TEOS-10, IOC et al., 2010), with conservative temperature and absolute salinity being then the prognostic variables. Radiative transfer in the water column is resolved using a chlorophyll-dependent three-waveband scheme as described in Lengaigne et al. (2007) and Séférian et al. (2019). Lateral diffusivity and viscosity are parameterized as in NOCS-ORCA1 (Danabasoglu et al., 2014). Parameterization of vertical mixing is also similar, with two notable exceptions in CNRM-CM6-1: mixing induced by breaking internal waves is parameterized following de Lavergne et al. (2016) and the Fox-Kemper et al. (2011) submesoscale mixed layer restratification scheme is activated. | F8: private | H8: atmosphere,land_surface | I8: HGRID002 | J8: VGRID003 | K8: REF001
B9: ocean_biogeochemistry | C9: Pelagic Interaction Scheme for Carbon and Ecosystem Studies model volume 2 version trace gases (PISCESv2-gas) | D9: PISCES | E9: Pelagic Interaction Scheme for Carbon and Ecosystem Studies model volume 2 version trace gases (PISCESv2-gas) derives from PISCESv2 as described in Aumont et al. (2015). PISCESv2-gas simulates the cycling of carbon, oxygen, and of the major nutrients determining phytoplankton growth (phosphate, nitrate, ammonium, iron and silicic acid). PISCESv2-gas also simulates dimethylsulfide (DMS) and nitrous oxide (N2O) tracers (see Bock et al. 2021 and Berthet et al. 2023). The carbon chemistry of the model is based on the Ocean Carbon Model Intercomparison Project (OMIP) protocol and the parametrization proposed by Wanninkhof (2014) is used to compute air-sea gas exchange of CO2, O2, DMS and N2O. PISCES includes a simple representation of the marine ecosystem with two phytoplankton size classes, representing nanophytoplankton and diatoms, as well as two zooplankton size classes, representing microzooplankton and mesozooplankton. Phytoplankton growth is limited by the availability of nutrients, temperature, and light. There are three non-living components of organic carbon in the model: semi-labile dissolved organic carbon (DOC), with a lifetime of several weeks to years, as well as large and small detrital particles, which are fuelled by mortality, aggregation, fecal pellet production and grazing. Biogenic silica and calcite particles are also included Nutrients and/or carbon are supplied to the ocean from three different sources: atmospheric deposition, rivers and sediment mobilization. These sources are explicitly included and vary in time apart the iron input of sediment. Atmospheric deposition of Fe, P and Si has been estimated from the INCA model and the one of N is coming from the Input4MIPS database. Riverine inputs are interactive in CNRM-ESM2-1 because the litter and soil carbon leaching in SURFEXv8.0 (see Section 2.4 for further details), is routed as dissolved organic carbon in CTRIP and supplied to the oceans as organic carbon by rivers in PISCESv2-gas. Since only the routing of dissolved organic carbon (DOC) is bounded in CNRM-ESM2-1, the supply of the other nutrients has been parameterized using the global average ratios of nitrogen-to-DOC (0.72), phosphorus-to-DOC (0.59), silicon-to-DOC (0.15) from Mayorga et al. (2010) and the global average ratios of DIC-to-DOC (1.48) and Alk-to-DOC (1.11) from Ludwig et al. (1996).River discharge of carbon and nutrients is taken from GlobalNews in NEMO standalone mode. Iron input from sediment mobilization has been parameterized as in Aumont et al. (2015). Nutrients and/or carbon are supplied to the ocean from three different sources: atmospheric deposition, rivers and sediment mobilization. These sources are explicitly included but do not vary in time apart from a climatological seasonal cycle for the atmospheric input. Atmospheric deposition (Fe, N, P and Si) has been estimated from the INCA model (Aumont et al, 2008). River discharge of carbon and nutrients is taken from Ludwig et al (1996). Iron input from sediment mobilization has been parameterized as in Aumont and Bopp (2006). PISCES is used here not only to compute air-sea fluxes of carbon, but also to compute the effect of a biophysical coupling: the chlorophyll concentration produced by the biological component retroacts on the ocean heat budget by modulating the absorption of light as well as the oceanic heating rate (see Lengaigne et al (2007) for a detailed description). | F9: https://gitlab.in2p3.fr/pisco/pisces-gas/pisces-gas | G9: ocean | H9: atmosphere,land_surface | I9: HGRID002 | J9: VGRID003 | K9: REF001,REF010,REF011
B10: sea_ice | C10: GELATO | D10: GELATO | E10: Global Experimental Leads and sea ice for ATmosphere and Ocean | F10: private | G10: ocean | I10: HGRID002 | J10: VGRID004 | K10: REF002

Sheet Horizontal Grid
A1: Grid ID | B1: grid_label | C1: grid | D1: description | E1: grid_mapping | F1: region | G1: temporal_refinement | H1: arrangement | I1: cell_variable_type | J1: mesh_location | K1: resolution_x | L1: resolution_y | M1: horizontal_units | N1: southernmost_latitude | O1: westernmost_longitude | P1: n_cells | Q1: truncation_method | R1: truncation_number | S1: resolution_range_km_min | T1: resolution_range_km_max | U1: mean_resolution_km | V1: nominal_resolution
A2: Unique ID (e.g., HGRID001) | B2: Free-text identifier (optional) | C2: Grid type (DROPDOWN from CV_Grid) | D2: Free-text description (optional) | E2: Coordinate reference system (DROPDOWN from CV_GridMapping) | F2: Geographical regions (comma-separated from CV_Region) | G2: Temporal refinement (DROPDOWN from CV_TemporalRefinement) | H2: Grid arrangement (DROPDOWN from CV_Arrangement) | I2: Variable types on cells (comma-separated from CV_CellVariableType) | J2: Mesh location for unstructured (DROPDOWN from CV_MeshLocation) | K2: Cell size in X direction | L2: Cell size in Y direction | M2: Units for resolution_x/y (DROPDOWN from CV_HorizontalUnits) | N2: Southernmost latitude (-90 to 90) | O2: Westernmost longitude (0 to <360) | P2: Total number of cells | Q2: Spectral truncation method (DROPDOWN from CV_TruncationMethod) | R2: Truncation wave number | S2: Min resolution in km | T2: Max resolution in km | U2: Mean resolution in km | V2: Nominal resolution (DROPDOWN from CV_NominalResolution)
A3: HGRID001 | C3: regular_latitude_longitude | E3: latitude_longitude | F3: global | G3: static | H3: arakawa_c | I3: mass | K3: 1.25 | L3: 0.9 | M3: degree | N3: -89.5 | O3: 0.5 | P3: 55296 | S3: 100.0 | T3: 170.1 | U3: 139.5 | V3: 100 km
A4: HGRID001 | B4: TL127 | C4: linear_spectral_gaussian | D4: TL127 | E4: latitude_longitude | F4: global | G4: static | H4: arakawa_a | K4: 1.4 | L4: 1.4 | M4: degree | N4: -88.927735 | O4: 0 | P4: 24572 | Q4: triangular | R4: 127 | S4: 155 | T4: 155 | U4: 155 | V4: 100 km
A5: HGRID002 | B5: eORCA1L75 | C5: tripolar | D5: eORCA1L75 | F5: global | G5: static | H5: arakawa_c | K5: not applicable | L5: not applicable | P5: 105704

Sheet Vertical Grid
A1: Grid ID | B1: coordinate | C1: description | D1: n_z | E1: n_z_range_min | F1: n_z_range_max | G1: bottom_layer_thickness | H1: top_layer_thickness | I1: top_of_model | J1: vertical_units
A2: Unique ID (e.g., VGRID001) | B2: Coordinate type (DROPDOWN from CV_Coordinate) | C2: Free-text description (optional) | D2: Number of layers (if constant) | E2: Min layers (if variable) | F2: Max layers (if variable) | G2: Bottom layer thickness | H2: Top layer thickness | I2: Top of model boundary | J2: Units (DROPDOWN from CV_VerticalUnits)
A3: VGRID001 | B3: atmosphere_hybrid_height_coordinate | D3: 85 | G3: 100 | H3: 10 | I3: 84763.34 | J3: m
A4: VGRID001 | B4: atmosphere_hybrid_sigma_pressure_coordinate | D4: 91 | G4: 240 | H4: 2 | I4: 0 | J4: Pa
A5: VGRID002 | B5: depth | C5: 14 soil layers (0.01, 0.04, 0.1, 0.2, 0.4, 0.6, 0.8, 1.0, 1.5, 2.0, 3.0, 5.0, 8.0, and 12.0 m) but the soil moisture profile is computed only over the rooting depth, from 0.2 (rocks) to 8 m (tropical forest) according to the land cover type, while the soil temperature is computed down to a depth of 12 m. Over the permafrost regions, all the 14 layers are solved in terms of moisture and temperature. See Decharme et al. (2019) for more details. | D5: 14 | G5: 4 | I5: 0.01 | J5: m
A6: VGRID003 | B6: ocean_sigma_z_coordinate | D6: 75 | G6: 200 | H6: 1 | J6: m
A7: VGRID004 | B7: height | D7: 10

Sheet References
A1: Reference ID | B1: citation | C1: doi
A2: Unique ID for this reference (e.g., REF001) | B2: Full human-readable citation | C2: DOI URL (must start with https://doi.org/)
A3: REF001 | B3: Smith, R. S., et al. (2021). Coupling the U.K. Earth System model... | C3: https://doi.org/10.1029/2021MS002520
A4: REF001 | B4: Séférian et al., 2019. Evaluation of CNRM Earth-System model, CNRM-ESM2-1 : role of Earth system processes in present-day and future climate, Journal of Advances in Modeling Earth Systems | C4: https://doi.org/10.1029/2019MS001791
A5: REF002 | B5: Voldoire, A. et al., 2019. Evaluation of CMIP6 DECK Experiments With CNRM-CM6-1, Journal of Advances in Modeling Earth Systems, 11, 2177–2213 | C5: https://doi.org/10.1029/2019MS001683
A6: REF003 | B6: Bossert et al, in rev, CNRM-ESM2-2: development and evaluation of an updated version of the CNRM-CERFACS Earth System Model. ESS Open Archive . October 06, 2025 | C6: DOI: 10.22541/essoar.175977424.42948487/v1
A7: REF004 | B7: TACTIC aerosol scheme and REPROBUS chemistry scheme : Michou et al, 2020. Presentâ€ Day and Historical Aerosol and Ozone Characteristics in CNRM CMIP6 Simulations, Journal of Advances in Modeling Earth Systems, https://doi.org/10.1029/2019MS001816 | C7: https://doi.org/10.1029/2019MS001816
A8: REF005 | B8: Roehrig, R., Beau, I., Saint-Martin, D., Alias, A., Decharme, B., Guérémy, J.-F., et al. (2020). The CNRM global atmosphere model ARPEGE-Climat 6.3: Description and evaluation. Journal of Advances in Modeling Earth Systems, 12, e2020MS002075. https://doi.org/10.1029/2020MS002075 | C8: https://doi.org/10.1029/2020MS002075
A9: REF006 | B9: ISBA-CTRIP Land Surface Physical Processes : Decharme B., Delire C., Minvielle M., Colin J., Vergnes J.-P., Alias A., Saint-Martin D., Séférian R., Sénési S., Voldoire A., (2019). Recent changes in the ISBA-CTRIP land surface system for use in the CNRM-CM6 climate model and in global offline hydrological applications. Journal of Advances in Modeling Earth Systems, 11. https://doi.org/10.1029/2018MS001545 | C9: https://doi.org/10.1029/2018MS001545
A10: REF007 | B10: ISBA-CTRIP Land Surface Biogeochemical Processes : Delire C., Séférian R., Decharme B., Alkama R., Calvet J.C., Carrer D., Gibelin A.L., Joetzjer E., Morel X., Rocher M., Tzanos D., 2020. The global land carbon cycle simulated with ISBA-CTRIP : improvements over the last decade, Journal of Advances in Modeling Earth Systems, https://doi.org/10.1029/2019MS001886 | C10: https://doi.org/10.1029/2019MS001886
A11: REF008 | B11: FLake lake scheme : Le Moigne et al, 2016. Impact of lake surface temperatures simulated by the FLake scheme in the CNRM-CM5 climate model, Tellus A: Dynamic Meteorology and Oceanography, 68:1, DOI: 10.3402/tellusa.v68.31274 | C11: DOI: 10.3402/tellusa.v68.31274
A12: REF009 | B12: SURFEX-OASIS coupling interface : Voldoire et al, 2017. SURFEX v8.0 interface with OASIS3-MCT to couple atmosphere with hydrology, ocean, waves and sea-ice models, from coastal to global scales, Geosci. Model Dev., 10, 4207-4227, https://doi.org/10.5194/gmd-10-4207-2017 | C12: https://doi.org/10.5194/gmd-10-4207-2017
... A14: REF011 | B14: Berthet, S., Jouanno, J., Séférian, R., Gehlen, M., and Llovel, W. : How does the phytoplankton–light feedback affect the marine N2O inventory ?, Earth Syst. Dynam., 14, 399–412, https://doi.org/10.5194/esd-14-399-2023, 2023. | C14: https://doi.org/10.5194/esd-14-399-2023

Sheet CV_Component
A1: 7.1 Component CV
A2: Component types for dynamic_components, prescribed_components, omitted_components, embedded_in, coupled_with
A4: Value | B4: Description
A5: aerosol | B5: The behaviour and evolution of aerosols suspended in the atmosphere.
A6: atmosphere | B6: Dynamical, thermodynamical, and physical processes in the atmosphere.
A7: atmospheric_chemistry | B7: The behaviour and evolution of the chemical composition of the atmosphere.
A8: land_surface | B8: Water, energy, and mass fluxes between the surface and the atmosphere.
A9: land_ice | B9: Frozen freshwater in glaciers, ice-caps, ice-sheets, and ice-shelves.
A10: ocean | B10: Dynamical, thermodynamical, and physical processes in the ocean.
A11: ocean_biogeochemistry | B11: Biological, geological, and chemical processes in the ocean.
A12: sea_ice | B12: Frozen seawater that floats on the ocean surface.

Sheet CV_Calendar
A1: 7.2 Calendar CV
A2: Calendar types for the top-level model calendar property
A4: Value | B4: Description
A5: standard | B5: Mixed Gregorian/Julian calendar (Gregorian after 1582-10-15, Julian before)
A6: proleptic_gregorian | B6: Gregorian rules extended to dates before 1582-10-15
A7: julian | B7: Julian calendar (leap year if divisible by 4, even if divisible by 100)
A8: 360_day | B8: All years are 360 days, divided into 30 day months
A9: 365_day | B9: No leap years, all years are 365 days
A10: 366_day | B10: All years are leap years (366 days)
A11: none | B11: No calendar

Sheet CV_Grid
A1: 7.3 Grid CV
A2: Horizontal grid types for the horizontal grid 'grid' property
A4: Value | B4: Description
A5: regular_latitude_longitude | B5: Rectilinear lat-lon grid with evenly spaced points
A6: regular_gaussian | B6: Gaussian grid with constant longitudinal points per latitude
A7: reduced_gaussian | B7: Gaussian grid with reduced points as poles are approached
A8: spectral_gaussian | B8: Transformation from spectral space to Gaussian grid
A9: spectral_reduced_gaussian | B9: Transformation from spectral space to reduced Gaussian
A10: linear_spectral_gaussian | B10: Spectral Gaussian, smallest wavelength = 2 grid points
A11: quadratic_spectral_gaussian | B11: Spectral Gaussian, smallest wavelength = 3 grid points
A12: cubic_octahedral_spectral_reduced_gaussian | B12: Spectral reduced Gaussian, smallest wavelength = 4 grid points, octahedron-based
A13: rotated_pole | B13: Regular lat-lon grid rotated to different north pole location
A14: stretched | B14: Higher resolution concentrated over area of interest
A15: displaced_pole | B15: Ocean grid with non-antipodean poles, northern pole over land
... A24: none | B24: No horizontal grid

Sheet CV_GridMapping
A1: 7.4 Grid Mapping CV
A2: Horizontal grid mappings (coordinate reference systems) - CF grid mapping names
A4: Value
A5: albers_conical_equal_area
A6: azimuthal_equidistant
A7: geostationary
A8: lambert_azimuthal_equal_area
A9: lambert_conformal_conic
A10: lambert_cylindrical_equal_area
A11: latitude_longitude
A12: orthographic
A13: polar_stereographic
... A18: vertical_perspective

Sheet CV_Region
A1: 7.5 Region CV
A2: Geographical regions for horizontal grid 'region' property
A4: Value | B4: Description
A5: antarctica | B5: Antarctica (CF standardised region)
A6: global | B6: Whole Earth's surface (CF standardised region)
A7: greenland | B7: Greenland (CF standardised region)
A8: limited_area | B8: Any contiguous subregion of Earth's surface

Sheet CV_TemporalRefinement
A1: 7.6 Temporal Refinement CV
A2: How grid cell distribution varies with time
A4: Value | B4: Description
A5: static | B5: Grid is held fixed, constant number of grid points
A6: dynamically_stretched | B6: Constant grid points, but can be dynamically relocated
A7: adaptive | B7: Variable number of grid points, refined/coarsened as needed

Sheet CV_Arrangement
A1: 7.7 Arrangement CV
A2: Relative locations of mass- and velocity-related quantities on grid (Arakawa grids)
A4: Value | B4: Description
A5: arakawa_a | B5: Mass and velocity at same location on each cell
A6: arakawa_b | B6: Velocity at corners of mass cells
A7: arakawa_c | B7: Velocity at centres of mass cell edges, perpendicular to edge
A8: arakawa_d | B8: Velocity at centres of mass cell edges, tangential to edge
A9: arakawa_e | B9: Mass at centres of velocity cell edges

Sheet CV_CellVariableType
A1: 7.8 Cell Variable Type CV
A2: Types of physical variables carried on horizontal grid cells
A4: Value | B4: Description
A5: mass | B5: Mass-related variables (thermodynamic and hydrodynamic quantities)
A6: velocity_x | B6: X component of velocity vector (longitude for spherical polar)
A7: velocity_y | B7: Y component of velocity vector (latitude for spherical polar)

Sheet CV_MeshLocation
A1: 7.9 Mesh Location CV
A2: Unstructured grid mesh locations for physical variables
A4: Value | B4: Description
A5: node | B5: Zero-dimensional point in space (vertex)
A6: edge | B6: One-dimensional line connecting two nodes (side)
A7: face | B7: Two-dimensional surface enclosed by edges (polygon)

Sheet CV_HorizontalUnits
A1: 7.10 Horizontal Units CV
A2: Physical units for resolution_x and resolution_y
A4: Value | B4: Description
A5: km | B5: kilometre (unit for length)
A6: degree | B6: degrees (unit for angular measure)

Sheet CV_TruncationMethod
A1: 7.11 Truncation Method CV
A2: Spherical harmonic truncation methods for spectral models
A4: Value | B4: Description
A5: triangular | B5: Triangular truncation
A6: rhomboidal | B6: Rhomboidal truncation

Sheet CV_NominalResolution
A1: 7.12 Nominal Resolution CV
A2: Nominal resolution based on mean_resolution_km value
A4: mean_resolution_km Range (R) | B4: nominal_resolution
A5: 0.036 ≤ R < 0.072 | B5: 0.05 km
A6: 0.072 ≤ R < 0.16 | B6: 0.1 km
A7: 0.16 ≤ R < 0.36 | B7: 0.25 km
A8: 0.36 ≤ R < 0.72 | B8: 0.5 km
A9: 0.72 ≤ R < 1.6 | B9: 1 km
A10: 1.6 ≤ R < 3.6 | B10: 2.5 km
A11: 3.6 ≤ R < 7.2 | B11: 5 km
A12: 7.2 ≤ R < 16 | B12: 10 km
A13: 16 ≤ R < 36 | B13: 25 km
A14: 36 ≤ R < 72 | B14: 50 km
A15: 72 ≤ R < 160 | B15: 100 km
... A21: 7200 ≤ R < 16000 | B21: 10000 km

Sheet CV_Coordinate
A1: 7.13 Coordinate CV
A2: Vertical grid coordinate types (CF standard names except where noted)
A4: Value | B4: Description
A5: none | B5: (Not a standard name) No vertical dimension
A6: height | B6: Vertical distance above the earth's surface
A7: geopotential_height | B7: Geopotential divided by standard acceleration due to gravity
A8: air_pressure | B8: Pressure in the medium of air
A9: air_potential_temperature | B9: Temperature of air parcel if moved dry adiabatically to standard pressure
A10: atmosphere_ln_pressure_coordinate | B10: Parametric atmosphere natural log pressure coordinate
A11: atmosphere_sigma_coordinate | B11: Parametric atmosphere sigma coordinate
A12: atmosphere_hybrid_sigma_pressure_coordinate | B12: Parametric atmosphere hybrid sigma pressure coordinate
A13: atmosphere_hybrid_height_coordinate | B13: Parametric atmosphere hybrid height coordinate
A14: atmosphere_sleve_coordinate | B14: Parametric atmosphere smooth vertical level coordinate
A15: depth | B15: Vertical distance below the earth's surface
... A25: z* | B25: (Not a standard name) z* coordinate of Adcroft and Campin (2004)

Sheet CV_VerticalUnits
A1: 7.14 Vertical Units CV
A2: Physical units for bottom_layer_thickness, top_layer_thickness, top_of_model
A4: Value | B4: Description
A5: m | B5: metre (unit for length)
A6: Pa | B6: pascal (unit for pressure)
A7: K | B7: kelvin (unit for temperature)
